newsApi/__init__.py
newsApi/service.py
newsApi/models/__init__.py
newsApi/models/request.py
newsApi/models/response.py
newsapi_python_client-0.2.4.dist-info/LICENSE
newsapi_python_client-0.2.4.dist-info/METADATA
newsapi_python_client-0.2.4.dist-info/WHEEL
newsapi_python_client-0.2.4.dist-info/top_level.txt
newsapi_python_client-0.2.4.dist-info/RECORD
