Metadata-Version: 2.1
Name: newsapi-python-client
Version: 0.2.4
Summary: A Python client to interact with News API from NewApi.org
Home-page: https://github.com/roachseb/NewsAPI-Python-Client
Author: Roach Sebastien
Author-email: sebastien.r.r@hotmail.com
License: MIT
Platform: UNKNOWN
Classifier: Development Status :: 3 - Alpha
Classifier: Intended Audience :: Developers
Classifier: Natural Language :: English
Classifier: License :: OSI Approved :: MIT License
Classifier: Programming Language :: Python :: 3
Classifier: Programming Language :: Python :: 3.6
Classifier: Programming Language :: Python :: 3.7
Classifier: Programming Language :: Python :: 3.8
Classifier: Programming Language :: Python :: 3.9
Classifier: Programming Language :: Python :: 3.10
License-File: LICENSE
Requires-Dist: requests
Requires-Dist: dataclasses ; python_version < "3.7"
